dvx/__init__.py
dvx/_version.py
dvx/cache.py
dvx/repo.py
dvx/cli/__init__.py
dvx/cli/diff.py
dvx/cli/external.py
dvx/cli/main.py
dvx/cli/run_cmd.py
dvx/cli/status.py
dvx/cli/transfer.py
dvx/cli/cache/__init__.py
dvx/cli/cache/dir.py
dvx/cli/cache/md5.py
dvx/cli/cache/path.py
dvx/run/__init__.py
dvx/run/artifact.py
dvx/run/dvc_files.py
dvx/run/executor.py
dvx/run/hash.py
dvx/run/status.py
dvx/shell/dvx.bash
dvx-0.1.0.dist-info/licenses/LICENSE
dvx-0.1.0.dist-info/METADATA
dvx-0.1.0.dist-info/WHEEL
dvx-0.1.0.dist-info/entry_points.txt
dvx-0.1.0.dist-info/top_level.txt
dvx-0.1.0.dist-info/RECORD
