Metadata-Version: 2.4
Name: dvx
Version: 0.1.0
Summary: Minimal data version control - a lightweight wrapper around DVC
Author-email: Ryan Williams <ryan@runsascoded.com>
License-Expression: Apache-2.0
Project-URL: Homepage, https://github.com/runsascoded/dvx
Project-URL: Repository, https://github.com/runsascoded/dvx
Keywords: data,version-control,dvc,machine-learning,reproducibility
Classifier: Development Status :: 3 - Alpha
Classifier: Intended Audience :: Developers
Classifier: Intended Audience :: Science/Research
Classifier: Programming Language :: Python :: 3
Classifier: Programming Language :: Python :: 3.10
Classifier: Programming Language :: Python :: 3.11
Classifier: Programming Language :: Python :: 3.12
Classifier: Programming Language :: Python :: 3.13
Classifier: Topic :: Scientific/Engineering
Classifier: Topic :: Software Development :: Version Control
Requires-Python: >=3.10
License-File: LICENSE
Requires-Dist: click>=8.0
Requires-Dist: dffs>=0.1.1
Requires-Dist: dvc>=3.50
Provides-Extra: s3
Requires-Dist: dvc-s3; extra == "s3"
Provides-Extra: gs
Requires-Dist: dvc-gs; extra == "gs"
Provides-Extra: azure
Requires-Dist: dvc-azure; extra == "azure"
Provides-Extra: ssh
Requires-Dist: dvc-ssh; extra == "ssh"
Provides-Extra: hdfs
Requires-Dist: dvc-hdfs; extra == "hdfs"
Provides-Extra: webdav
Requires-Dist: dvc-webdav; extra == "webdav"
Provides-Extra: webhdfs
Requires-Dist: dvc-webhdfs; extra == "webhdfs"
Provides-Extra: oss
Requires-Dist: dvc-oss; extra == "oss"
Provides-Extra: all
Requires-Dist: dvc-s3; extra == "all"
Requires-Dist: dvc-gs; extra == "all"
Requires-Dist: dvc-azure; extra == "all"
Requires-Dist: dvc-ssh; extra == "all"
Requires-Dist: dvc-hdfs; extra == "all"
Requires-Dist: dvc-webdav; extra == "all"
Requires-Dist: dvc-webhdfs; extra == "all"
Requires-Dist: dvc-oss; extra == "all"
Provides-Extra: dev
Requires-Dist: pytest>=7; extra == "dev"
Requires-Dist: pytest-cov; extra == "dev"
Requires-Dist: ruff; extra == "dev"
Requires-Dist: mypy; extra == "dev"
Dynamic: license-file
